tekorrect/__init__.py
tekorrect/pangu.py
tekorrect/tekorrect.py
tekorrect-0.0.3.dist-info/LICENSE
tekorrect-0.0.3.dist-info/METADATA
tekorrect-0.0.3.dist-info/WHEEL
tekorrect-0.0.3.dist-info/entry_points.txt
tekorrect-0.0.3.dist-info/top_level.txt
tekorrect-0.0.3.dist-info/RECORD
