Metadata-Version: 2.1
Name: tekorrect
Version: 0.0.3
Summary: 用於給已經完成的 Markdown 遍寫的文檔進行優化，它會將壹些非標準，或不推薦的排版方式，進行自動格式化、標準化。
Home-page: https://github.com/n0vad3v/Tekorrect
Author: Nova Kwok
Author-email: noc@nova.moe
License: UNKNOWN
Keywords: pangu text-spacing spacing text typesetting readability chinese japanese korean obsessive-compulsive-disorder ocd paranoia
Platform: UNKNOWN
Classifier: Programming Language :: Python :: 3
Classifier: Natural Language :: Chinese (Traditional)
Classifier: Natural Language :: Chinese (Simplified)
Classifier: Natural Language :: Japanese
Classifier: Natural Language :: Korean
Classifier: Topic :: Education
Classifier: Topic :: Software Development :: Internationalization
Classifier: Topic :: Text Processing
Classifier: Topic :: Text Processing :: General
Classifier: Topic :: Text Processing :: Linguistic
Classifier: Topic :: Utilities
Classifier: License :: OSI Approved :: GNU General Public License v3 (GPLv3)
Classifier: Operating System :: OS Independent
Requires-Dist: pangu
